omegamath01/OmegaMath01.py
omegamath01/__init__.py
omegamath01/info.py
OmegaMath01-1.0.8.dist-info/LICENSE.txt
OmegaMath01-1.0.8.dist-info/METADATA
OmegaMath01-1.0.8.dist-info/WHEEL
OmegaMath01-1.0.8.dist-info/top_level.txt
OmegaMath01-1.0.8.dist-info/RECORD
