Metadata-Version: 2.1
Name: OmegaMath01
Version: 1.0.8
Summary: A small package of useful miscellaneuos functions, including drawing helpers,primefactorization functions, and others. Install Directions: pip install OmegaMath01
Home-page: https://github.com/GrandMoff100/MathFunctions
Author: Quantum_Wizard
Author-email: minecraftcrusher100@gmail.com
License: UNKNOWN
Platform: UNKNOWN
Classifier: Programming Language :: Python :: 3
Classifier: License :: OSI Approved :: MIT License
Requires-Python: >=3.6
